MANIFEST.in
README.md
requirements.txt
setup.py
vspkgenerator/__init__.py
vspkgenerator.egg-info/PKG-INFO
vspkgenerator.egg-info/SOURCES.txt
vspkgenerator.egg-info/dependency_links.txt
vspkgenerator.egg-info/entry_points.txt
vspkgenerator.egg-info/requires.txt
vspkgenerator.egg-info/top_level.txt
vspkgenerator/conf/config.ini
vspkgenerator/conf/mapping.ini
vspkgenerator/vanilla/csharp/LICENSE
vspkgenerator/vanilla/csharp/README.md
vspkgenerator/vanilla/csharp/__code_header
vspkgenerator/vanilla/csharp/__attributes_defaults/attrs_defaults.ini
vspkgenerator/vanilla/csharp/__attributes_defaults/attrs_types.ini
vspkgenerator/vanilla/go/LICENSE
vspkgenerator/vanilla/go/README.md
vspkgenerator/vanilla/go/__code_header
vspkgenerator/vanilla/go/__attributes_defaults/attrs_defaults.ini
vspkgenerator/vanilla/html/README.md
vspkgenerator/vanilla/html/usage.html
vspkgenerator/vanilla/java/LICENSE
vspkgenerator/vanilla/java/README.md
vspkgenerator/vanilla/java/__code_header
vspkgenerator/vanilla/java/__attributes_defaults/attrs_defaults.ini
vspkgenerator/vanilla/java/__attributes_defaults/attrs_types.ini
vspkgenerator/vanilla/objj/LICENSE
vspkgenerator/vanilla/objj/README.md
vspkgenerator/vanilla/objj/__code_header
vspkgenerator/vanilla/objj/__attributes_defaults/attrs_defaults.ini
vspkgenerator/vanilla/python/LICENSE
vspkgenerator/vanilla/python/README.md
vspkgenerator/vanilla/python/__code_header
vspkgenerator/vanilla/python/requirements.txt
vspkgenerator/vanilla/python/__attributes_defaults/attrs_defaults.ini
vspkgenerator/vanilla/python/__overrides/nudomain.override.py
vspkgenerator/vanilla/python/__overrides/nudomaintemplate.override.py
vspkgenerator/vanilla/python/__overrides/nuegressaclentrytemplate.override.py
vspkgenerator/vanilla/python/__overrides/nugateway.override.py
vspkgenerator/vanilla/python/__overrides/nugatewaytemplate.override.py
vspkgenerator/vanilla/python/__overrides/nuingressaclentrytemplate.override.py
vspkgenerator/vanilla/python/__overrides/nuingressacltemplate.override.py
vspkgenerator/vanilla/python/__overrides/nuingressadvfwdentrytemplate.override.py
vspkgenerator/vanilla/python/__overrides/nuingressadvfwdtemplate.override.py
