Metadata-Version: 1.0
Name: vspkgenerator
Version: 1.5.0
Summary: VSPK Generator
Home-page: https://github.com/nuagenetworks/vspkgenerator
Author: Nuage Networks
Author-email: opensource@nuagenetworks.net
License: UNKNOWN
Platform: UNKNOWN
